datasette_metasearch/__init__.py
datasette_metasearch/cli.py
datasette_metasearch/utils.py
datasette_metasearch/templates/beta.html
datasette_metasearch-1.0.1.dist-info/METADATA
datasette_metasearch-1.0.1.dist-info/WHEEL
datasette_metasearch-1.0.1.dist-info/entry_points.txt
datasette_metasearch-1.0.1.dist-info/top_level.txt
datasette_metasearch-1.0.1.dist-info/RECORD
