Metadata-Version: 2.4
Name: datasette-metasearch
Version: 1.0.1
Summary: Build a search index across content from multiple SQLite database tables and run faceted searches against it using Datasette
Author: Brendan Samek
License: Apache-2.0
Project-URL: Homepage, https://github.com/xrendan/datasette-metasearch
Project-URL: Issues, https://github.com/dogsheep/datasette-metasearch/issues
Project-URL: CI, https://github.com/dogsheep/datasette-metasearch/actions
Project-URL: Changelog, https://github.com/dogsheep/datasette-metasearch/releases
Requires-Python: >=3.7
Requires-Dist: datasette>=0.50.2
Requires-Dist: click
Requires-Dist: PyYAML
Requires-Dist: sqlite-utils>=3.0
Provides-Extra: test
Requires-Dist: pytest; extra == "test"
Requires-Dist: pytest-asyncio; extra == "test"
Requires-Dist: httpx; extra == "test"
Requires-Dist: beautifulsoup4; extra == "test"
Requires-Dist: html5lib; extra == "test"
